hunterpass/__init__.py
hunterpass/generate.py
hunterpass/main.py
hunterpass-0.0.6.4.dist-info/LICENSE
hunterpass-0.0.6.4.dist-info/METADATA
hunterpass-0.0.6.4.dist-info/WHEEL
hunterpass-0.0.6.4.dist-info/entry_points.txt
hunterpass-0.0.6.4.dist-info/top_level.txt
hunterpass-0.0.6.4.dist-info/RECORD
