Metadata-Version: 2.1
Name: hunterpass
Version: 0.0.6.4
Summary: Generate dictionary with AI
Author: rafa_dev (Rafael Macedo)
Author-email: <rafaelrodriguesmacedo2004@gmail.com>
Keywords: python,dictionary,generate,llm,security,hashes,hash,cybersecurity,cyber,hacking
Classifier: Development Status :: 1 - Planning
Classifier: Intended Audience :: Developers
Classifier: Programming Language :: Python :: 3
Classifier: Operating System :: Unix
Classifier: Operating System :: MacOS :: MacOS X
Classifier: Operating System :: Microsoft :: Windows
License-File: LICENSE
Requires-Dist: openai
Requires-Dist: argparse
